ip2locationio/__init__.py
ip2locationio/common.py
ip2locationio/configuration.py
ip2locationio/domainwhois.py
ip2locationio/ipgeolocation.py
ip2locationio-1.0.0.dist-info/LICENSE.TXT
ip2locationio-1.0.0.dist-info/METADATA
ip2locationio-1.0.0.dist-info/WHEEL
ip2locationio-1.0.0.dist-info/top_level.txt
ip2locationio-1.0.0.dist-info/RECORD
