Metadata-Version: 2.1
Name: ip2locationio
Version: 1.0.0
Summary: IP2Location.io Python SDK to get geolocation info from IPv4 and IPv6 address.
Home-page: https://github.com/ip2location/ip2location-io-python
Author: IP2Location
Author-email: support@ip2location.com
Classifier: Development Status :: 5 - Production/Stable
Classifier: Intended Audience :: Developers
Classifier: Topic :: Software Development :: Libraries :: Python Modules
Classifier: Programming Language :: Python :: 3.5
Classifier: Programming Language :: Python :: 3.6
Classifier: Programming Language :: Python :: 3.7
Classifier: Programming Language :: Python :: 3.8
Classifier: Programming Language :: Python :: 3.9
Classifier: Programming Language :: Python :: 3.10
Classifier: Programming Language :: Python :: 3.11
Classifier: License :: OSI Approved :: MIT License
Classifier: Operating System :: OS Independent
License-File: LICENSE.TXT
